README.rst
setup.cfg
setup.py
xpath/__init__.py
xpath/compat.py
xpath/dsl.py
xpath/expression.py
xpath/html.py
xpath/literal.py
xpath/renderer.py
xpath/utils.py
xpath/version.py
xpath_py.egg-info/PKG-INFO
xpath_py.egg-info/SOURCES.txt
xpath_py.egg-info/dependency_links.txt
xpath_py.egg-info/requires.txt
xpath_py.egg-info/top_level.txt