Metadata-Version: 1.1
Name: xpath-py
Version: 0.1.2
Summary: Python library for generating XPath expressions
Home-page: https://github.com/elliterate/xpath.py
Author: Ian Lesperance
Author-email: ian@elliterate.com
License: MIT
Keywords: xpath
Platform: UNKNOWN
Classifier: Development Status :: 4 - Beta
Classifier: Intended Audience :: Developers
Classifier: Intended Audience :: Information Technology
Classifier: License :: OSI Approved :: MIT License
Classifier: Natural Language :: English
Classifier: Programming Language :: Python :: 2.7
Classifier: Programming Language :: Python :: 3.5
Classifier: Topic :: Software Development :: Code Generators
Classifier: Topic :: Software Development :: Libraries :: Python Modules
Classifier: Topic :: Text Processing :: Markup :: HTML
Classifier: Topic :: Text Processing :: Markup :: XML
Classifier: Topic :: Utilities
